dockai/__init__.py
dockai/main.py
dockai/cli/__init__.py
dockai/cli/commands.py
dockai/core/__init__.py
dockai/core/config_manager.py
dockai/core/formatter.py
dockai/core/log_parser.py
dockai/core/ollama_engine.py
dockai/core/openai_engine.py
dockai/plugins/__init__.py
dockai/plugins/api.py
dockai/plugins/loader.py
dockai/plugins/example/plugin.json
dockai/plugins/example/plugin.py
dockai/plugins/telemetry/license_manager.py
dockai/plugins/telemetry/plugin.json
dockai/plugins/telemetry/plugin.py
dockai/plugins/telemetry/schema.sql
dockai/plugins/telemetry/telemetry_plugin.py
dockai/server/__init__.py
dockai/server/auth.py
dockai/server/billing.py
dockai/server/main.py
dockai/server/usage_tracker.py
dockai/utils/__init__.py
dockai/utils/cache.py
dockai/utils/docker_utils.py
dockai/utils/env_loader.py
dockai-0.5.3.dist-info/licenses/LICENSE
dockai-0.5.3.dist-info/METADATA
dockai-0.5.3.dist-info/WHEEL
dockai-0.5.3.dist-info/entry_points.txt
dockai-0.5.3.dist-info/top_level.txt
dockai-0.5.3.dist-info/RECORD
