Metadata-Version: 2.4
Name: dockai
Version: 0.5.3
Summary: DockAI – AI-powered Docker Log Analysis Tool (CLI + Cloud)
Author: Ahmet Atakan
Author-email: ahmetatakan.tech@gmail.com
License: Apache License 2.0
Classifier: License :: OSI Approved :: Apache Software License
Classifier: Programming Language :: Python :: 3
Classifier: Topic :: System :: Monitoring
Requires-Python: >=3.9
License-File: LICENSE
Requires-Dist: click<9.0,>=8.1
Requires-Dist: docker<7.0,>=6.1
Requires-Dist: openai<2.0,>=1.0
Requires-Dist: requests<3.0,>=2.31
Requires-Dist: termcolor<3.0,>=2.0
Requires-Dist: fastapi<1.0,>=0.110
Requires-Dist: uvicorn<1.0,>=0.23
Requires-Dist: stripe<10,>=9
Requires-Dist: python-dotenv<2.0,>=1.0
Requires-Dist: PyJWT<3.0,>=2.0
Provides-Extra: cloud
Requires-Dist: openai<2.0,>=1.0; extra == "cloud"
Requires-Dist: stripe<10,>=9; extra == "cloud"
Provides-Extra: dev
Requires-Dist: pytest; extra == "dev"
Requires-Dist: black; extra == "dev"
Requires-Dist: ruff; extra == "dev"
Requires-Dist: pip-tools; extra == "dev"
Dynamic: author
Dynamic: author-email
Dynamic: classifier
Dynamic: description
Dynamic: description-content-type
Dynamic: license
Dynamic: license-file
Dynamic: provides-extra
Dynamic: requires-dist
Dynamic: requires-python
Dynamic: summary
